shiva/__init__.py
shiva/art.py
shiva/const.py
shiva/main.py
shiva/run.py
shiva/shiva_cli.py
shiva/commands/__init__.py
shiva/commands/test.py
shiva/commands/common/__init__.py
shiva/commands/common/project.py
shiva/commands/common/shiva_run.py
shiva/common/__init__.py
shiva/common/args.py
shiva/common/base.py
shiva/common/cli.py
shiva/common/commands.py
shiva/common/config.py
shiva/common/daemon.py
shiva/common/dispatcher.py
shiva/common/driver.py
shiva/common/logging.py
shiva/common/modules_helper.py
shiva/common/policy.py
shiva/common/rmq_routing.py
shiva/common/scan.py
shiva/common/workers.py
shiva/data_types/__init__.py
shiva/dispatchers/__init__.py
shiva/dispatchers/daemon.py
shiva/dispatchers/metrics.py
shiva/dispatchers/rmq.py
shiva/dispatchers/web.py
shiva/drivers/__init__.py
shiva/drivers/api/__init__.py
shiva/drivers/api/s3_aiobotocore.py
shiva/drivers/databases/__init__.py
shiva/drivers/databases/mongodb.py
shiva/drivers/databases/postgres.py
shiva/drivers/databases/redis.py
shiva/drivers/esb/__init__.py
shiva/drivers/esb/rmq.py
shiva/examples/workers/__init__.py
shiva/examples/workers/benchmark/__init__.py
shiva/examples/workers/benchmark/rmq_bench.py
shiva/examples/workers/mydaemon/__init__.py
shiva/examples/workers/mydaemon/daemon_1.py
shiva/examples/workers/web/__init__.py
shiva/examples/workers/web/healthcheck.py
shiva/lib/__init__.py
shiva/lib/tools.py
shiva/proto/__init__.py
shiva/proto/bpm.py
shiva/proto/rmq_simple.py
shiva/workers/__init__.py
shiva/workers/metrics/__init__.py
shiva/workers/metrics/some_metrics.py
shiva/workers/waiter/__init__.py
shiva/workers/waiter/waiter.py
shiva/workers/web/__init__.py
shiva/workers/web/healthcheck.py
shivad-0.4.18.dist-info/licenses/LICENSE
tests/test_cli.py
tests/test_dispatchers.py
tests/test_protocols.py
shivad-0.4.18.dist-info/METADATA
shivad-0.4.18.dist-info/WHEEL
shivad-0.4.18.dist-info/entry_points.txt
shivad-0.4.18.dist-info/top_level.txt
shivad-0.4.18.dist-info/RECORD
