Metadata-Version: 2.4
Name: shivad
Version: 0.4.18
Summary: A modern, async Python framework for distributed systems and microservices.
Author-email: Boris Soldatov <djsaff@gmail.com>
License-Expression: MIT
Project-URL: homepage, https://github.com/Zl0n1k/shivad
Project-URL: bug-tracker, https://github.com/Zl0n1k/shivad/issues
Project-URL: documentation, https://github.com/Zl0n1k/shivad#readme
Classifier: Programming Language :: Python :: 3
Classifier: Programming Language :: Python :: 3.12
Classifier: Operating System :: OS Independent
Classifier: Development Status :: 4 - Beta
Classifier: Intended Audience :: Developers
Classifier: Topic :: Software Development :: Libraries :: Application Frameworks
Requires-Python: >=3.11
License-File: LICENSE
Requires-Dist: aiomisc<15.0.0,>=14.0.0
Requires-Dist: aio-pika<10.0.0,>=9.0.5
Requires-Dist: aioredis<2.0.0,>=1.3.1
Requires-Dist: asyncpg<1.0.0,>=0.28.0
Requires-Dist: PyYAML<7.0.0,>=6.0.1
Requires-Dist: orjson<4.0.0,>=3.5.2
Requires-Dist: fastapi
Requires-Dist: argparse<2.0.0,>=1.4.0
Requires-Dist: uvicorn<1.0.0,>=0.13.4
Requires-Dist: loguru<1.0.0,>=0.7.2
Requires-Dist: sentry-sdk<2.0.0,>=1.0.0
Requires-Dist: flatdict<5.0.0,>=4.0.1
Requires-Dist: typer<1.0.0,>=0.3.2
Requires-Dist: art<6.0.0,>=5.2
Requires-Dist: marshmallow<4.0.0,>=3.13.0
Requires-Dist: motor<4.0.0,>=3.6.0
Requires-Dist: aiobotocore<3.0.0,>=2.16.0
Requires-Dist: packaging<24.0,>=23.0
Requires-Dist: twine<4.0.0,>=3.8.0
Requires-Dist: keyring<24.0.0,>=23.5.0
Requires-Dist: uvloop<1.0.0,>=0.17.0; sys_platform == "darwin" or sys_platform == "linux"
Requires-Dist: fastapi-restful
Requires-Dist: prometheus-client<1.0.0,>=0.18.0
Requires-Dist: mako<2.0.0,>=1.3.0
Requires-Dist: starlette<1.0.0,>=0.37.2
Requires-Dist: fastapi-utils[all]<1.0.0,>=0.8.0
Requires-Dist: pytest>=8.4.1
Requires-Dist: setuptools>=80.9.0
Requires-Dist: pytest-asyncio>=1.0.0
Provides-Extra: dev
Requires-Dist: ipython<9.0.0,>=8.22.1; extra == "dev"
Dynamic: license-file
